fastapi_motor/__init__.py
fastapi_motor-0.1.0.dist-info/METADATA
fastapi_motor-0.1.0.dist-info/WHEEL
fastapi_motor-0.1.0.dist-info/top_level.txt
fastapi_motor-0.1.0.dist-info/RECORD
